<Annotation><folder>VOC1900</folder><filename>19_326851_279959jpg</filename><path>VOC1900/JPEGImages/19_326851_279959.jpg</path><object><name>buildings</name><bndbox><xmin>243</xmin><ymin>15</ymin><xmax>11</xmax><ymax>243</ymax></bndbox></object><object><name>buildings</name><bndbox><xmin>14</xmin><ymin>1</ymin><xmax>55</xmax><ymax>219</ymax></bndbox></object><object><name>buildings</name><bndbox><xmin>255</xmin><ymin>30</ymin><xmax>22</xmax><ymax>8</ymax></bndbox></object><object><name>buildings</name><bndbox><xmin>232</xmin><ymin>73</ymin><xmax>1</xmax><ymax>47</ymax></bndbox></object><object><name>buildings</name><bndbox><xmin>63</xmin><ymin>45</ymin><xmax>91</xmax><ymax>16</ymax></bndbox></object><object><name>buildings</name><bndbox><xmin>158</xmin><ymin>36</ymin><xmax>196</xmax><ymax>254</ymax></bndbox></object><object><name>buildings</name><bndbox><xmin>67</xmin><ymin>221</ymin><xmax>88</xmax><ymax>193</ymax></bndbox></object><object><name>buildings</name><bndbox><xmin>35</xmin><ymin>235</ymin><xmax>66</xmax><ymax>202</ymax></bndbox></object><object><name>buildings</name><bndbox><xmin>85</xmin><ymin>218</ymin><xmax>109</xmax><ymax>187</ymax></bndbox></object><object><name>buildings</name><bndbox><xmin>205</xmin><ymin>171</ymin><xmax>230</xmax><ymax>138</ymax></bndbox></object><object><name>buildings</name><bndbox><xmin>101</xmin><ymin>123</ymin><xmax>134</xmax><ymax>83</ymax></bndbox></object><object><name>buildings</name><bndbox><xmin>253</xmin><ymin>114</ymin><xmax>28</xmax><ymax>81</ymax></bndbox></object><object><name>buildings</name><bndbox><xmin>241</xmin><ymin>126</ymin><xmax>0</xmax><ymax>108</ymax></bndbox></object><object><name>buildings</name><bndbox><xmin>88</xmin><ymin>28</ymin><xmax>116</xmax><ymax>1</ymax></bndbox></object><object><name>buildings</name><bndbox><xmin>71</xmin><ymin>163</ymin><xmax>92</xmax><ymax>138</ymax></bndbox></object><object><name>buildings</name><bndbox><xmin>146</xmin><ymin>201</ymin><xmax>165</xmax><ymax>185</ymax></bndbox></object><object><name>buildings</name><bndbox><xmin>240</xmin><ymin>120</ymin><xmax>7</xmax><ymax>102</ymax></bndbox></object><object><name>buildings</name><bndbox><xmin>241</xmin><ymin>97</ymin><xmax>5</xmax><ymax>86</ymax></bndbox></object><object><name>buildings</name><bndbox><xmin>178</xmin><ymin>118</ymin><xmax>234</xmax><ymax>72</ymax></bndbox></object><object><name>buildings</name><bndbox><xmin>82</xmin><ymin>245</ymin><xmax>99</xmax><ymax>230</ymax></bndbox></object><object><name>buildings</name><bndbox><xmin>14</xmin><ymin>97</ymin><xmax>63</xmax><ymax>50</ymax></bndbox></object><object><name>buildings</name><bndbox><xmin>45</xmin><ymin>15</ymin><xmax>63</xmax><ymax>253</ymax></bndbox></object><object><name>buildings</name><bndbox><xmin>220</xmin><ymin>212</ymin><xmax>248</xmax><ymax>173</ymax></bndbox></object><size><width>256</width><height>256</height><depth>3</depth></size></Annotation>